helium_api_wrapper/DataObjects.py
helium_api_wrapper/ResultHandler.py
helium_api_wrapper/__init__.py
helium_api_wrapper/__main__.py
helium_api_wrapper/challenges.py
helium_api_wrapper/devices.py
helium_api_wrapper/endpoint.py
helium_api_wrapper/hotspots.py
helium_api_wrapper/py.typed
helium_api_wrapper-0.0.1.dev1675266436.dist-info/METADATA
helium_api_wrapper-0.0.1.dev1675266436.dist-info/entry_points.txt
helium_api_wrapper-0.0.1.dev1675266436.dist-info/WHEEL
helium_api_wrapper-0.0.1.dev1675266436.dist-info/LICENSE
helium_api_wrapper-0.0.1.dev1675266436.dist-info/RECORD
