Metadata-Version: 2.1
Name: helium-api-wrapper
Version: 0.0.1.dev1675266436
Summary: Helium Api Wrapper
Home-page: https://github.com/emergotechnologies/helium-api-wrapper
License: MIT
Author: Lukas Huber
Author-email: lukas.huber@fh-kufstein.ac.at
Requires-Python: >=3.8,<4.0
Classifier: Development Status :: 3 - Alpha
Classifier: License :: OSI Approved :: MIT License
Classifier: Programming Language :: Python :: 3
Classifier: Programming Language :: Python :: 3.8
Classifier: Programming Language :: Python :: 3.9
Classifier: Programming Language :: Python :: 3.10
Classifier: Programming Language :: Python :: 3.11
Requires-Dist: click (>=8.0.1)
Requires-Dist: haversine (>=2.7.0,<3.0.0)
Requires-Dist: pandas (>=1.5.1,<2.0.0)
Requires-Dist: pyarrow (>=10.0.0,<11.0.0)
Requires-Dist: pydantic (>=1.10.2,<2.0.0)
Requires-Dist: python-dotenv (>=0.21.0,<0.22.0)
Requires-Dist: sphinx-rtd-theme (>=1.1.1,<2.0.0)
Requires-Dist: types-click (>=7.1.8,<8.0.0)
Requires-Dist: types-requests (>=2.28.11.5,<3.0.0.0)
Project-URL: Changelog, https://github.com/emergotechnologies/helium-api-wrapper/releases
Project-URL: Documentation, https://helium-api-wrapper.readthedocs.io
Project-URL: Repository, https://github.com/emergotechnologies/helium-api-wrapper
